{"openapi":"3.0.1","servers":[{"url":"/","description":"Default Server URL"}],"paths":{"/public/stripe/webhooks":{"post":{"tags":["stripe-webhook-controller"],"operationId":"handleWebhook","parameters":[{"name":"Stripe-Signature","in":"header","required":true,"schema":{"type":"string"}}],"requestBody":{"content":{"application/json":{"schema":{"type":"string"}}},"required":true},"responses":{"400":{"description":"Bad Request","content":{"*/*":{"schema":{"$ref":"#/components/schemas/ProblemDetail"}}}},"403":{"description":"Forbidden"},"404":{"description":"Not Found","content":{"*/*":{"schema":{"$ref":"#/components/schemas/ProblemDetail"}}}},"200":{"description":"OK","content":{"*/*":{"schema":{"type":"string"}}}}}}},"/public/sendgrid/webhook/inbound-parse":{"post":{"tags":["sendgrid-webhook-controller"],"operationId":"inboundParse","parameters":[{"name":"text","in":"query","required":true,"schema":{"type":"string"}}],"requestBody":{"content":{"application/json":{"schema":{"required":["headers"],"type":"object","properties":{"headers":{"type":"string"}}}}}},"responses":{"400":{"description":"Bad Request","content":{"*/*":{"schema":{"$ref":"#/components/schemas/ProblemDetail"}}}},"403":{"description":"Forbidden"},"404":{"description":"Not Found","content":{"*/*":{"schema":{"$ref":"#/components/schemas/ProblemDetail"}}}},"201":{"description":"Created"}}}},"/public/organizations":{"post":{"tags":["organization-controller"],"operationId":"register","requestBody":{"content":{"application/json":{"schema":{"$ref":"#/components/schemas/OrganizationToRegister"}}},"required":true},"responses":{"400":{"description":"Bad Request","content":{"*/*":{"schema":{"$ref":"#/components/schemas/ProblemDetail"}}}},"403":{"description":"Forbidden"},"404":{"description":"Not Found","content":{"*/*":{"schema":{"$ref":"#/components/schemas/ProblemDetail"}}}},"200":{"description":"OK"}}}},"/public/accounts/passwords/resets":{"post":{"tags":["public-account-controller"],"operationId":"performPasswordReset","requestBody":{"content":{"application/json":{"schema":{"$ref":"#/components/schemas/PasswordResetData"}}},"required":true},"responses":{"400":{"description":"Bad Request","content":{"*/*":{"schema":{"$ref":"#/components/schemas/ProblemDetail"}}}},"403":{"description":"Forbidden"},"404":{"description":"Not Found","content":{"*/*":{"schema":{"$ref":"#/components/schemas/ProblemDetail"}}}},"200":{"description":"OK"}}}},"/public/accounts/passwords/resets/requests":{"post":{"tags":["public-account-controller"],"operationId":"requestPasswordReset","requestBody":{"content":{"application/json":{"schema":{"$ref":"#/components/schemas/PasswordResetRequest"}}},"required":true},"responses":{"400":{"description":"Bad Request","content":{"*/*":{"schema":{"$ref":"#/components/schemas/ProblemDetail"}}}},"403":{"description":"Forbidden"},"404":{"description":"Not Found","content":{"*/*":{"schema":{"$ref":"#/components/schemas/ProblemDetail"}}}},"200":{"description":"OK"}}}},"/organizations/{organizationId}/api-keys":{"get":{"tags":["organization-api-key-controller"],"operationId":"list_2","parameters":[{"name":"organizationId","in":"path","required":true,"schema":{"type":"string"}}],"responses":{"400":{"description":"Bad Request","content":{"*/*":{"schema":{"$ref":"#/components/schemas/ProblemDetail"}}}},"403":{"description":"Forbidden"},"404":{"description":"Not Found","content":{"*/*":{"schema":{"$ref":"#/components/schemas/ProblemDetail"}}}},"200":{"description":"OK","content":{"*/*":{"schema":{"type":"array","items":{"$ref":"#/components/schemas/OrganizationApiKeyEntry"}}}}}}},"post":{"tags":["organization-api-key-controller"],"operationId":"generate","parameters":[{"name":"organizationId","in":"path","required":true,"schema":{"type":"string"}}],"requestBody":{"content":{"application/json":{"schema":{"$ref":"#/components/schemas/GenerateKeyRequest"}}},"required":true},"responses":{"400":{"description":"Bad Request","content":{"*/*":{"schema":{"$ref":"#/components/schemas/ProblemDetail"}}}},"403":{"description":"Forbidden"},"404":{"description":"Not Found","content":{"*/*":{"schema":{"$ref":"#/components/schemas/ProblemDetail"}}}},"200":{"description":"OK","content":{"*/*":{"schema":{"$ref":"#/components/schemas/ApiKeyValue"}}}}}}},"/logout":{"post":{"tags":["fake-authorization-controller-for-swagger"],"operationId":"fakeLogout","responses":{"400":{"description":"Bad Request","content":{"*/*":{"schema":{"$ref":"#/components/schemas/ProblemDetail"}}}},"403":{"description":"Forbidden"},"404":{"description":"Not Found","content":{"*/*":{"schema":{"$ref":"#/components/schemas/ProblemDetail"}}}},"200":{"description":"OK"}}}},"/login":{"post":{"tags":["login-endpoint"],"requestBody":{"content":{"application/json":{"schema":{"type":"object","properties":{"username":{"type":"string"},"password":{"type":"string"}}}}}},"responses":{"200":{"description":"OK"},"403":{"description":"Forbidden"}}}},"/api/conversions":{"post":{"tags":["conversions-controller"],"operationId":"initialize","parameters":[{"name":"Api-Key","in":"header"},{"name":"OrganizationId","in":"header"}],"requestBody":{"content":{"application/json":{"schema":{"$ref":"#/components/schemas/ConversionProperties"}}},"required":true},"responses":{"400":{"description":"Bad Request","content":{"*/*":{"schema":{"$ref":"#/components/schemas/ProblemDetail"}}}},"403":{"description":"Forbidden"},"404":{"description":"Not Found","content":{"*/*":{"schema":{"$ref":"#/components/schemas/ProblemDetail"}}}},"200":{"description":"OK","content":{"*/*":{"schema":{"$ref":"#/components/schemas/InitializedConversionId"}}}}}}},"/api/conversions/{conversionId}/convert":{"post":{"tags":["conversions-controller"],"operationId":"performConversion","parameters":[{"name":"Api-Key","in":"header"},{"name":"OrganizationId","in":"header"},{"name":"conversionId","in":"path","required":true,"schema":{"type":"string"}}],"requestBody":{"content":{"multipart/form-data":{"schema":{"required":["index"],"type":"object","properties":{"index":{"type":"string","format":"binary"}}}}}},"responses":{"400":{"description":"Bad Request","content":{"*/*":{"schema":{"$ref":"#/components/schemas/ProblemDetail"}}}},"403":{"description":"Forbidden"},"404":{"description":"Not Found","content":{"*/*":{"schema":{"$ref":"#/components/schemas/ProblemDetail"}}}},"200":{"description":"OK","content":{"*/*":{"schema":{"$ref":"#/components/schemas/Unit"}}}}}}},"/api/conversions/{conversionId}/assets":{"post":{"tags":["conversions-controller"],"operationId":"attachAssetToConversion","parameters":[{"name":"Api-Key","in":"header"},{"name":"OrganizationId","in":"header"},{"name":"conversionId","in":"path","required":true,"schema":{"type":"string"}}],"requestBody":{"content":{"multipart/form-data":{"schema":{"required":["asset"],"type":"object","properties":{"asset":{"type":"string","format":"binary"}}}}}},"responses":{"400":{"description":"Bad Request","content":{"*/*":{"schema":{"$ref":"#/components/schemas/ProblemDetail"}}}},"403":{"description":"Forbidden"},"404":{"description":"Not Found","content":{"*/*":{"schema":{"$ref":"#/components/schemas/ProblemDetail"}}}},"200":{"description":"OK","content":{"*/*":{"schema":{"$ref":"#/components/schemas/Unit"}}}}}}},"/accounts/password":{"post":{"tags":["account-controller"],"operationId":"changePassword","requestBody":{"content":{"application/json":{"schema":{"$ref":"#/components/schemas/ChangePasswordRequest"}}},"required":true},"responses":{"400":{"description":"Bad Request","content":{"*/*":{"schema":{"$ref":"#/components/schemas/ProblemDetail"}}}},"403":{"description":"Forbidden"},"404":{"description":"Not Found","content":{"*/*":{"schema":{"$ref":"#/components/schemas/ProblemDetail"}}}},"200":{"description":"OK"}}}},"/organizations":{"get":{"tags":["organization-controller"],"operationId":"list","responses":{"400":{"description":"Bad Request","content":{"*/*":{"schema":{"$ref":"#/components/schemas/ProblemDetail"}}}},"403":{"description":"Forbidden"},"404":{"description":"Not Found","content":{"*/*":{"schema":{"$ref":"#/components/schemas/ProblemDetail"}}}},"200":{"description":"OK","content":{"*/*":{"schema":{"type":"array","items":{"$ref":"#/components/schemas/AccessibleOrganization"}}}}}}}},"/organizations/{organizationId}/subscription":{"get":{"tags":["subscription-controller"],"operationId":"getSubscription","parameters":[{"name":"organizationId","in":"path","required":true,"schema":{"type":"string"}}],"responses":{"400":{"description":"Bad Request","content":{"*/*":{"schema":{"$ref":"#/components/schemas/ProblemDetail"}}}},"403":{"description":"Forbidden"},"404":{"description":"Not Found","content":{"*/*":{"schema":{"$ref":"#/components/schemas/ProblemDetail"}}}},"200":{"description":"OK","content":{"*/*":{"schema":{"$ref":"#/components/schemas/HasActiveSubscriptionResponse"}}}}}}},"/organizations/{organizationId}/subscription/manage":{"get":{"tags":["subscription-controller"],"operationId":"goToSubscriptionManagement","parameters":[{"name":"organizationId","in":"path","required":true,"schema":{"type":"string"}}],"responses":{"400":{"description":"Bad Request","content":{"*/*":{"schema":{"$ref":"#/components/schemas/ProblemDetail"}}}},"403":{"description":"Forbidden"},"404":{"description":"Not Found","content":{"*/*":{"schema":{"$ref":"#/components/schemas/ProblemDetail"}}}},"200":{"description":"OK","content":{"*/*":{"schema":{"$ref":"#/components/schemas/Unit"}}}}}}},"/organizations/{organizationId}/quotas":{"get":{"tags":["quotas-controller"],"operationId":"getCurrentQuotas","parameters":[{"name":"organizationId","in":"path","required":true,"schema":{"type":"string"}}],"responses":{"400":{"description":"Bad Request","content":{"*/*":{"schema":{"$ref":"#/components/schemas/ProblemDetail"}}}},"403":{"description":"Forbidden"},"404":{"description":"Not Found","content":{"*/*":{"schema":{"$ref":"#/components/schemas/ProblemDetail"}}}},"200":{"description":"OK","content":{"*/*":{"schema":{"$ref":"#/components/schemas/CurrentQuotas"}}}}}}},"/organizations/{organizationId}/conversions":{"get":{"tags":["conversion-log-controller"],"operationId":"list_1","parameters":[{"name":"organizationId","in":"path","required":true,"schema":{"type":"string"}},{"name":"page","in":"query","description":"Zero-based page index (0..N)","required":false,"schema":{"minimum":0,"type":"integer","default":0}},{"name":"size","in":"query","description":"The size of the page to be returned","required":false,"schema":{"minimum":1,"type":"integer","default":20}},{"name":"sort","in":"query","description":"Sorting criteria in the format: property,(asc|desc). Default sort order is ascending. Multiple sort criteria are supported.","required":false,"schema":{"type":"array","items":{"type":"string"}}}],"responses":{"400":{"description":"Bad Request","content":{"*/*":{"schema":{"$ref":"#/components/schemas/ProblemDetail"}}}},"403":{"description":"Forbidden"},"404":{"description":"Not Found","content":{"*/*":{"schema":{"$ref":"#/components/schemas/ProblemDetail"}}}},"200":{"description":"OK","content":{"*/*":{"schema":{"$ref":"#/components/schemas/PagedModelConversionLog"}}}}}}},"/organizations/{organizationId}/conversions/stats":{"get":{"tags":["conversion-log-controller"],"operationId":"stats","parameters":[{"name":"organizationId","in":"path","required":true,"schema":{"type":"string"}},{"name":"interval","in":"query","required":true,"schema":{"type":"string","enum":["LAST_DAY","LAST_7_DAYS","LAST_30_DAYS"]}}],"responses":{"400":{"description":"Bad Request","content":{"*/*":{"schema":{"$ref":"#/components/schemas/ProblemDetail"}}}},"403":{"description":"Forbidden"},"404":{"description":"Not Found","content":{"*/*":{"schema":{"$ref":"#/components/schemas/ProblemDetail"}}}},"200":{"description":"OK","content":{"*/*":{"schema":{"type":"array","items":{"$ref":"#/components/schemas/Stat"}}}}}}}},"/me":{"get":{"tags":["account-controller"],"operationId":"me","responses":{"400":{"description":"Bad Request","content":{"*/*":{"schema":{"$ref":"#/components/schemas/ProblemDetail"}}}},"403":{"description":"Forbidden"},"404":{"description":"Not Found","content":{"*/*":{"schema":{"$ref":"#/components/schemas/ProblemDetail"}}}},"200":{"description":"OK","content":{"*/*":{"schema":{"$ref":"#/components/schemas/AccountDetails"}}}}}}},"/api/conversions/{conversionId}":{"get":{"tags":["conversions-controller"],"operationId":"getConversionResult","parameters":[{"name":"Api-Key","in":"header"},{"name":"OrganizationId","in":"header"},{"name":"conversionId","in":"path","required":true,"schema":{"type":"string"}}],"responses":{"400":{"description":"Bad Request","content":{"*/*":{"schema":{"$ref":"#/components/schemas/ProblemDetail"}}}},"403":{"description":"Forbidden"},"404":{"description":"Not Found","content":{"*/*":{"schema":{"$ref":"#/components/schemas/ProblemDetail"}}}},"200":{"description":"OK","content":{"*/*":{"schema":{"type":"string","format":"binary"}}}}}}},"/organizations/{organizationId}/api-keys/{keyId}":{"delete":{"tags":["organization-api-key-controller"],"operationId":"delete","parameters":[{"name":"organizationId","in":"path","required":true,"schema":{"type":"string"}},{"name":"keyId","in":"path","required":true,"schema":{"type":"string"}}],"responses":{"400":{"description":"Bad Request","content":{"*/*":{"schema":{"$ref":"#/components/schemas/ProblemDetail"}}}},"403":{"description":"Forbidden"},"404":{"description":"Not Found","content":{"*/*":{"schema":{"$ref":"#/components/schemas/ProblemDetail"}}}},"200":{"description":"OK"}}}}},"components":{"schemas":{"ProblemDetail":{"type":"object","properties":{"type":{"type":"string","format":"uri"},"title":{"type":"string"},"status":{"type":"integer","format":"int32"},"detail":{"type":"string"},"instance":{"type":"string","format":"uri"},"properties":{"type":"object","additionalProperties":{"type":"object"}}}},"OrganizationToRegister":{"required":["name","password","username"],"type":"object","properties":{"username":{"type":"string"},"password":{"type":"string"},"name":{"type":"string"}}},"PasswordResetData":{"required":["accountId","newPassword","token"],"type":"object","properties":{"accountId":{"type":"string"},"token":{"type":"string"},"newPassword":{"type":"string"}}},"PasswordResetRequest":{"required":["email"],"type":"object","properties":{"email":{"type":"string"}}},"GenerateKeyRequest":{"required":["label"],"type":"object","properties":{"label":{"type":"string"}}},"ApiKeyValue":{"required":["value"],"type":"object","properties":{"value":{"type":"string"}}},"LoginCredentials":{"required":["password","username"],"type":"object","properties":{"username":{"type":"string"},"password":{"type":"string"}}},"ConversionProperties":{"required":["margin","scale"],"type":"object","properties":{"format":{"type":"string","enum":["Letter","Legal","Tabloid","Ledger","A0","A1","A2","A3","A4","A5","A6"]},"headerFile":{"type":"string"},"footerFile":{"type":"string"},"scale":{"type":"number","format":"float"},"margin":{"$ref":"#/components/schemas/Margin"},"landscape":{"type":"boolean"}}},"Margin":{"required":["bottom","left","right","top"],"type":"object","properties":{"top":{"type":"integer","format":"int32"},"bottom":{"type":"integer","format":"int32"},"left":{"type":"integer","format":"int32"},"right":{"type":"integer","format":"int32"}}},"InitializedConversionId":{"required":["id"],"type":"object","properties":{"id":{"type":"string"}}},"Unit":{"type":"object"},"ChangePasswordRequest":{"required":["newPassword","oldPassword"],"type":"object","properties":{"oldPassword":{"type":"string"},"newPassword":{"type":"string"}}},"AccessibleOrganization":{"required":["id","name"],"type":"object","properties":{"id":{"type":"string"},"name":{"type":"string"}}},"HasActiveSubscriptionResponse":{"required":["customerEmail","customerReferenceId","hasActiveSubscription"],"type":"object","properties":{"hasActiveSubscription":{"type":"boolean"},"customerReferenceId":{"type":"string"},"customerEmail":{"type":"string"}}},"CurrentQuotas":{"required":["availableConversions","conversionSizeLimit","conversionThrottling","conversions","isConversionQuotaAvailable"],"type":"object","properties":{"conversions":{"type":"integer","format":"int32"},"availableConversions":{"type":"integer","format":"int32"},"conversionThrottling":{"$ref":"#/components/schemas/Throttling"},"conversionSizeLimit":{"type":"integer","format":"int64"},"endDate":{"type":"string","format":"date-time"},"isConversionQuotaAvailable":{"type":"boolean"}}},"Throttling":{"required":["count","duration"],"type":"object","properties":{"count":{"type":"integer","format":"int32"},"duration":{"type":"object","properties":{"seconds":{"type":"integer","format":"int64"},"zero":{"type":"boolean"},"nano":{"type":"integer","format":"int32"},"negative":{"type":"boolean"},"positive":{"type":"boolean"},"units":{"type":"array","items":{"type":"object","properties":{"durationEstimated":{"type":"boolean"},"timeBased":{"type":"boolean"},"dateBased":{"type":"boolean"}}}}}}}},"ConversionAssetAttached":{"required":["fileName","size"],"type":"object","allOf":[{"$ref":"#/components/schemas/LogEntryDetails"},{"type":"object","properties":{"fileName":{"type":"string"},"size":{"type":"integer","format":"int64"}}}]},"ConversionFailed":{"required":["reason","stacktrace"],"type":"object","allOf":[{"$ref":"#/components/schemas/LogEntryDetails"},{"type":"object","properties":{"reason":{"type":"string"},"stacktrace":{"type":"string"}}}]},"ConversionInitialized":{"required":["properties"],"type":"object","allOf":[{"$ref":"#/components/schemas/LogEntryDetails"},{"type":"object","properties":{"properties":{"$ref":"#/components/schemas/ConversionProperties"}}}]},"ConversionLog":{"required":["entries","id"],"type":"object","properties":{"conversionId":{"type":"string","writeOnly":true},"id":{"type":"string"},"entries":{"type":"array","items":{"$ref":"#/components/schemas/ConversionLogEntry"}}}},"ConversionLogEntry":{"required":["details","occurredAt"],"type":"object","properties":{"occurredAt":{"type":"string","format":"date-time"},"details":{"oneOf":[{"$ref":"#/components/schemas/ConversionAssetAttached"},{"$ref":"#/components/schemas/ConversionFailed"},{"$ref":"#/components/schemas/ConversionInitialized"},{"$ref":"#/components/schemas/ConversionPerformed"},{"$ref":"#/components/schemas/ConversionResultFetched"}]}}},"ConversionPerformed":{"required":["duration","resultFileSize"],"type":"object","allOf":[{"$ref":"#/components/schemas/LogEntryDetails"},{"type":"object","properties":{"resultFileSize":{"type":"integer","format":"int64"},"duration":{"type":"object","properties":{"seconds":{"type":"integer","format":"int64"},"zero":{"type":"boolean"},"nano":{"type":"integer","format":"int32"},"negative":{"type":"boolean"},"positive":{"type":"boolean"},"units":{"type":"array","items":{"type":"object","properties":{"durationEstimated":{"type":"boolean"},"timeBased":{"type":"boolean"},"dateBased":{"type":"boolean"}}}}}}}}]},"ConversionResultFetched":{"required":["resultSize"],"type":"object","allOf":[{"$ref":"#/components/schemas/LogEntryDetails"},{"type":"object","properties":{"resultSize":{"type":"integer","format":"int64"}}}]},"LogEntryDetails":{"required":["type"],"type":"object","properties":{"type":{"type":"string"}},"discriminator":{"propertyName":"type"}},"PageMetadata":{"type":"object","properties":{"size":{"type":"integer","format":"int64"},"number":{"type":"integer","format":"int64"},"totalElements":{"type":"integer","format":"int64"},"totalPages":{"type":"integer","format":"int64"}}},"PagedModelConversionLog":{"type":"object","properties":{"content":{"type":"array","items":{"$ref":"#/components/schemas/ConversionLog"}},"page":{"$ref":"#/components/schemas/PageMetadata"}}},"Stat":{"required":["entryCount","intervalStart"],"type":"object","properties":{"entryCount":{"type":"integer","format":"int64"},"intervalStart":{"type":"string","format":"date-time"}}},"OrganizationApiKeyEntry":{"required":["id","label"],"type":"object","properties":{"id":{"type":"string"},"label":{"type":"string"}}},"AccountDetails":{"required":["id","username"],"type":"object","properties":{"id":{"type":"string"},"username":{"type":"string"}}}}}}